colorify/__init__.py
colorify/core.py
pycolorify-0.1.0.dist-info/METADATA
pycolorify-0.1.0.dist-info/WHEEL
pycolorify-0.1.0.dist-info/top_level.txt
pycolorify-0.1.0.dist-info/RECORD
