Metadata-Version: 2.4
Name: pycolorify
Version: 0.1.0
Summary: A simple color manipulation and conversion library
Home-page: https://github.com/yourusername/colorify
Author: Your Name
License: MIT
Requires-Python: >=3.6
Dynamic: author
Dynamic: home-page
Dynamic: license
Dynamic: requires-python
Dynamic: summary
